django_telegram_support/__init__.py
django_telegram_support/apps.py
django_telegram_support/conf.py
django_telegram_support/forms.py
django_telegram_support/telegram.py
django_telegram_support/urls.py
django_telegram_support/views.py
django_telegram_support/templates/django_telegram_support/support_form.html
django_telegram_support-0.1.0.dist-info/licenses/LICENSE
django_telegram_support-0.1.0.dist-info/METADATA
django_telegram_support-0.1.0.dist-info/WHEEL
django_telegram_support-0.1.0.dist-info/top_level.txt
django_telegram_support-0.1.0.dist-info/RECORD
