Metadata-Version: 2.4
Name: django-telegram-support
Version: 0.1.0
Summary: Reusable Django support/contact form that sends messages to Telegram.
Author-email: Andrei Mazur <agrshkv@gmail.com>
License: MIT
Keywords: django,telegram,support,contact,form
Classifier: Development Status :: 4 - Beta
Classifier: Framework :: Django
Classifier: Framework :: Django :: 4.2
Classifier: Framework :: Django :: 5.0
Classifier: Intended Audience :: Developers
Classifier: License :: OSI Approved :: MIT License
Classifier: Programming Language :: Python
Classifier: Programming Language :: Python :: 3
Classifier: Programming Language :: Python :: 3 :: Only
Classifier: Programming Language :: Python :: 3.10
Classifier: Programming Language :: Python :: 3.11
Classifier: Programming Language :: Python :: 3.12
Classifier: Topic :: Internet :: WWW/HTTP
Requires-Python: >=3.8
License-File: LICENSE
Requires-Dist: Django>=4.2
Requires-Dist: requests>=2.31
Dynamic: license-file
